pand8/__init__.py
pand8/extras.py
pand8/handler.py
mad8_pandas-1.1.1.dist-info/LICENSE
mad8_pandas-1.1.1.dist-info/METADATA
mad8_pandas-1.1.1.dist-info/WHEEL
mad8_pandas-1.1.1.dist-info/top_level.txt
mad8_pandas-1.1.1.dist-info/RECORD
