Metadata-Version: 2.1
Name: mad8-pandas
Version: 1.1.1
Summary: load mad8 output with pandas
Home-page: https://github.com/st-walker/mad8-pandas
Author: Stuart Walker
Author-email: stuart.derek.walker@gmail.com
License: MIT
Keywords: mad8 pandas twiss
Classifier: Development Status :: 5 - Production/Stable
Classifier: Intended Audience :: Science/Research
Classifier: License :: OSI Approved :: MIT License
Classifier: Natural Language :: English
Classifier: Operating System :: OS Independent
Classifier: Programming Language :: Python :: 3 :: Only
Classifier: Programming Language :: Python :: 3.7
Classifier: Programming Language :: Python :: 3.8
Classifier: Programming Language :: Python :: 3.9
Classifier: Programming Language :: Python :: 3.10
Classifier: Programming Language :: Python :: 3.11
Classifier: Topic :: Scientific/Engineering
Classifier: Topic :: Software Development :: Libraries :: Python Modules
Classifier: Typing :: Typed
License-File: LICENSE
Requires-Dist: pandas
Requires-Dist: fortranformat
Requires-Dist: numpy
